LICENSE
LICENSE.txt
README.md
setup.cfg
setup.py
TabularDataInvestigation/TabularDataInvestigation.py
TabularDataInvestigation/__init__.py
TabularDataInvestigation/tdi.py
TabularDataInvestigation.egg-info/PKG-INFO
TabularDataInvestigation.egg-info/SOURCES.txt
TabularDataInvestigation.egg-info/dependency_links.txt
TabularDataInvestigation.egg-info/requires.txt
TabularDataInvestigation.egg-info/top_level.txt
TabularDataInvestigation/__pycache__/TabularDataInvestigation.cpython-310.pyc
TabularDataInvestigation/__pycache__/__init__.cpython-310.pyc
TabularDataInvestigation/__pycache__/tdi.cpython-310.pyc